[{"item_id":"m26151838746","price_text":"\u00a5 4,155","price":4155,"user_name":"olli_olleio\u00ae\ufe0e\ua4b0\u2022\u0361\u032b\u2022\u0f7c\ua4b1","user_url":"https:\/\/www.mercari.com\/jp\/u\/160221403\/","item_state":"\u76ee\u7acb\u3063\u305f\u50b7\u3084\u6c5a\u308c\u306a\u3057","delivery_charge_burden":"\u9001\u6599\u8fbc\u307f(\u51fa\u54c1\u8005\u8ca0\u62c5)","delivery_method":"\u666e\u901a\u90f5\u4fbf(\u5b9a\u5f62\u3001\u5b9a\u5f62\u5916)","shipment_date_criterion":"2~3\u65e5\u3067\u767a\u9001"},{"item_id":"m60161622562","price_text":"\u00a5 5,222","price":5222,"user_name":"\u306a\u304a\u3068","user_url":"https:\/\/www.mercari.com\/jp\/u\/946990609\/","item_state":"\u76ee\u7acb\u3063\u305f\u50b7\u3084\u6c5a\u308c\u306a\u3057","delivery_charge_burden":"\u9001\u6599\u8fbc\u307f(\u51fa\u54c1\u8005\u8ca0\u62c5)","delivery_method":"\u672a\u5b9a","shipment_date_criterion":"2~3\u65e5\u3067\u767a\u9001"}]